{
  "Groups": [
    {
      "Name": "Main",
      "DisplayName": "Options",
      "Elements": [
	  		{
		"Name": "IncludeDir0",
		"DisplayName": "Style",
		"Description": [
		"Changes style of Sonic's model.",
				],
            "Type": "Style",
		    "MinValue": null,
		    "MaxValue": null,
            "DefaultValue": "./Sonic/Unleashed/"
		}
      ]
    }
  ],
  "Enums": {
    "Style": [
      {
        "DisplayName": "Unleashed",
        "Value": "./Sonic/Unleashed/",
      },
      {
        "DisplayName": "Cel-shaded",
        "Value": "./Sonic/Cel-shaded/",
      }
    ]
  },
  "IniFile": "mod.ini"
}
